preface/__init__.py
preface/concurrency.py
preface/dict.py
preface/py.typed
preface-0.1.5.dist-info/LICENSE
preface-0.1.5.dist-info/WHEEL
preface-0.1.5.dist-info/METADATA
preface-0.1.5.dist-info/RECORD
