Metadata-Version: 2.1
Name: preface
Version: 0.1.5
Summary: Some helper functions and classes that I want in nearly every project.
Author-email: Samuel Stevens <samuel.robert.stevens@gmail.com>
Classifier: License :: OSI Approved :: MIT License
Project-URL: Home, https://github.com/samuelstevens/preface
